{
    "one_dm": [
        {
            "index": 1,
            "num_balls": 3,
            "ball_positions": [1, 2, 4],
            "angles": [194, 173, 140],
            "preemption": true,
            "last_collision": 2.46,
            "cause_ball": 2,
            
            "jitter": {
                "x": [-10, 8, -20],
                "y": [3, 30, 11]
            },
            "file_name": "videos/complex/one_dm/stim1.mp4"
        },
        {
            "index": 2,
            "num_balls": 4,
            "ball_positions": [1, 2, 4],
            "angles": [164, 148, 140],
            "preemption": true,
            "last_collision": 2.41,
            "cause_ball": 1,
            
            "jitter": {
                "x": [-30, -28, -10],
                "y": [60, 100, 41]
            },
            "file_name": "videos/complex/one_dm/stim2.mp4"
        },
        {
            "index": 3,
            "num_balls": 3,
            "ball_positions": [2, 3, 5],
            "angles": [150, 189, 150],
            "preemption": true,
            "last_collision": 2.34,
            "cause_ball": 3,
            
            "jitter": {
                "x": [3, 12, 20],
                "y": [-40, -29, 0]
            },
            "file_name": "videos/complex/one_dm/stim3.mp4"
        },
        {
            "index": 4,
            "num_balls": 3,
            "ball_positions": [1, 3, 4],
            "angles": [185, 209, 143],
            "preemption": true,
            "cause_ball": 3,
            "last_collision": 1.92,
            "jitter": {
                "x": [20, 20, 20],
                "y": [0, 0, 0]
            },
            "file_name": "videos/complex/one_dm/stim4.mp4"
        },
        {
            "index": 5,
            "num_balls": 3,
            "ball_positions": [3, 4, 5],
            "angles": [180, 164, 212],
            "preemption": true,
            "last_collision": 2.48,
            "cause_ball": 1,
            
            "jitter": {
                "x": [20, 40, 20],
                "y": [3, 30, 41]
            },
            "file_name": "videos/complex/one_dm/stim5.mp4"
        }
    ],

    "two_dm": [
        {
            "index": 1,
            "num_balls": 3,
            "ball_positions": [1, 4, 5],
            "angles": [200, 133, 150],
            "preemption": true,
            "last_collision": 1.71,
            "cause_ball": 3,
            "jitter": {
                "x": [-2, -8, 20],
                "y": [30, -6, -3]
            },
            "file_name": "videos/complex/two_dm/stim1.mp4"
        },
        {
            "index": 2,
            "num_balls": 4,
            "ball_positions": [1, 2, 4],
            "angles": [174, 148, 140],
            "preemption": true,
            "last_collision": 0.9,
            "cause_ball": 2,
            
            "jitter": {
                "x": [-10, 8, -20],
                "y": [3, 30, 11]
            },
            "file_name": "videos/complex/two_dm/stim2.mp4"
        },
        {
            "index": 3,
            "num_balls": 3,
            "ball_positions": [1, 3, 5],
            "angles": [155, 189, 143],
            "preemption": true,
            "cause_ball": 2,
            "last_collision": 1.0,
            "jitter": {
                "x": [20, 20, 20],
                "y": [0, 0, 0]
            },
            "file_name": "videos/complex/two_dm/stim3.mp4"
        },
        {
            "index": 4,
            "num_balls": 3,
            "ball_positions": [1, 3, 5],
            "angles": [189, 220, 140],
            "preemption": true,
            "cause_ball": 3,
            "last_collision": 0.49,
            "jitter": {
                "x": [20, 20, 20],
                "y": [0, 0, 0]
            },
            "file_name": "videos/complex/two_dm/stim4.mp4"
        },
        {
            "index": 5,
            "num_balls": 3,
            "ball_positions": [2, 4, 5],
            "angles": [166, 208, 170],
            "preemption": true,
            "cause_ball": 1,
            "last_collision": 1.16,
            "jitter": {
                "x": [20, 40, 20],
                "y": [0, 0, 0]
            },
            "file_name": "videos/complex/two_dm/stim5.mp4"
        }
    ],

    "three_dm": [
        {
            "index": 1,
            "num_balls": 3,
            "ball_positions": [1, 3, 5],
            "angles": [224, 149, 200],
            "preemption": true,
            "last_collision": 0.86,
            "cause_ball": 1,
            
            "jitter": {
                "x": [-20, -20, -20],
                "y": [0, 0, 0]
            },
            "file_name": "videos/complex/three_dm/stim1.mp4"
        },
        {
            "index": 2,
            "num_balls": 3,
            "ball_positions": [2, 4, 5],
            "angles": [166, 208, 215],
            "preemption": true,
            "cause_ball": 3,
            "last_collision": 1.46,
            "jitter": {
                "x": [40, 40, 20],
                "y": [0, 0, 0]
            },
            "file_name": "videos/complex/three_dm/stim2.mp4"
        },
        {
            "index": 3,
            "num_balls": 3,
            "ball_positions": [1, 2, 3],
            "angles": [224, 214, 204],
            "preemption": true,
            "last_collision": 1.01,
            "cause_ball": 3,
            
            "jitter": {
                "x": [30, 30, -20],
                "y": [3, 30, 11]
            },
            "file_name": "videos/complex/three_dm/stim3.mp4"
        },
        {
            "index": 4,
            "num_balls": 3,
            "ball_positions": [1, 3, 5],
            "angles": [154, 164, 204],
            "preemption": true,
            "last_collision": 0.57,
            "cause_ball": 2,
            
            "jitter": {
                "x": [30, 30, 20],
                "y": [3, 30, 11]
            },
            "file_name": "videos/complex/three_dm/stim4.mp4"
        },
        {
            "index": 5,
            "num_balls": 3,
            "ball_positions": [2, 4, 5],
            "angles": [160, 164, 212],
            "preemption": true,
            "last_collision": 0.94,
            "cause_ball": 1,
            
            "jitter": {
                "x": [20, 40, 20],
                "y": [3, 30, 41]
            },
            "file_name": "videos/complex/three_dm/stim5.mp4"
        }
    ]

    
    
}